[
    {
        "name": "Female10148",
        "gender": "F",
        "piperVoiceID": 4
    },
    {
        "name": "Female2037",
        "gender": "F",
        "piperVoiceID": 2
    },
    {
        "name": "Male9565",
        "gender": "M",
        "piperVoiceID": 3
    },
    {
        "name": "Female5424",
        "gender": "F",
        "piperVoiceID": 12
    },
    {
        "name": "Male10904",
        "gender": "M",
        "piperVoiceID": 148
    },
    {
        "name": "Female10791",
        "gender": "F",
        "piperVoiceID": 69
    },
    {
        "name": "Male8659",
        "gender": "M",
        "piperVoiceID": 59
    },
    {
        "name": "Female4174",
        "gender": "F",
        "piperVoiceID": 14
    },
    {
        "name": "Male10536",
        "gender": "M",
        "piperVoiceID": 191
    },
    {
        "name": "Female8294",
        "gender": "F",
        "piperVoiceID": 64
    },
    {
        "name": "Female10087",
        "gender": "F",
        "piperVoiceID": 63
    },
    {
        "name": "Male9132",
        "gender": "M",
        "piperVoiceID": 9
    },
    {
        "name": "Male10947",
        "gender": "M",
        "piperVoiceID": 220
    },
    {
        "name": "Female9639",
        "gender": "F",
        "piperVoiceID": 19
    },
    {
        "name": "Female10433",
        "gender": "F",
        "piperVoiceID": 216
    },
    {
        "name": "Male5753",
        "gender": "M",
        "piperVoiceID": 11
    },
    {
        "name": "Female10179",
        "gender": "F",
        "piperVoiceID": 36
    },
    {
        "name": "Male6880",
        "gender": "M",
        "piperVoiceID": 47
    },
    {
        "name": "Female10819",
        "gender": "F",
        "piperVoiceID": 205
    },
    {
        "name": "Female10614",
        "gender": "F",
        "piperVoiceID": 192
    },
    {
        "name": "Female1649",
        "gender": "F",
        "piperVoiceID": 26
    },
    {
        "name": "Female5244",
        "gender": "F",
        "piperVoiceID": 33
    },
    {
        "name": "Male11413",
        "gender": "M",
        "piperVoiceID": 190
    },
    {
        "name": "Male11546",
        "gender": "M",
        "piperVoiceID": 152
    },
    {
        "name": "Female11497",
        "gender": "F",
        "piperVoiceID": 200
    },
    {
        "name": "Male11299",
        "gender": "M",
        "piperVoiceID": 139
    },
    {
        "name": "Male10364",
        "gender": "M",
        "piperVoiceID": 213
    },
    {
        "name": "Male11481",
        "gender": "M",
        "piperVoiceID": 203
    },
    {
        "name": "Male11328",
        "gender": "M",
        "piperVoiceID": 207
    },
    {
        "name": "Female10625",
        "gender": "F",
        "piperVoiceID": 151
    },
    {
        "name": "Male11480",
        "gender": "M",
        "piperVoiceID": 150
    },
    {
        "name": "Male11355",
        "gender": "M",
        "piperVoiceID": 229
    },
    {
        "name": "Male12415",
        "gender": "M",
        "piperVoiceID": 16
    },
    {
        "name": "Male12275",
        "gender": "M",
        "piperVoiceID": 25
    },
    {
        "name": "Male11869",
        "gender": "M",
        "piperVoiceID": 221
    },
    {
        "name": "Female11990",
        "gender": "F",
        "piperVoiceID": 46
    },
    {
        "name": "Male11927",
        "gender": "M",
        "piperVoiceID": 18
    },
    {
        "name": "Female11870",
        "gender": "F",
        "piperVoiceID": 211
    },
    {
        "name": "Female12174",
        "gender": "F",
        "piperVoiceID": 230
    },
    {
        "name": "Female11772",
        "gender": "F",
        "piperVoiceID": 201
    },
    {
        "name": "Male11920",
        "gender": "M",
        "piperVoiceID": 208
    },
    {
        "name": "Female11987",
        "gender": "F",
        "piperVoiceID": 233
    },
    {
        "name": "Male12335",
        "gender": "M",
        "piperVoiceID": 222
    },
    {
        "name": "Female9706",
        "gender": "F",
        "piperVoiceID": 174
    },
    {
        "name": "Female12461",
        "gender": "F",
        "piperVoiceID": 188
    },
    {
        "name": "Male12417",
        "gender": "M",
        "piperVoiceID": 212
    },
    {
        "name": "Male12776",
        "gender": "M",
        "piperVoiceID": 169
    },
    {
        "name": "Female12500",
        "gender": "F",
        "piperVoiceID": 223
    },
    {
        "name": "Male13626",
        "gender": "M",
        "piperVoiceID": 156
    },
    {
        "name": "Male13726",
        "gender": "M",
        "piperVoiceID": 171
    },
    {
        "name": "Female12899",
        "gender": "F",
        "piperVoiceID": 40
    },
    {
        "name": "Female13755",
        "gender": "F",
        "piperVoiceID": 224
    },
    {
        "name": "Male252",
        "gender": "M",
        "piperVoiceID": 8
    },
    {
        "name": "Female20",
        "gender": "F",
        "piperVoiceID": 38
    },
    {
        "name": "Male2034",
        "gender": "M",
        "piperVoiceID": 142
    },
    {
        "name": "Male2602",
        "gender": "M",
        "piperVoiceID": 13
    },
    {
        "name": "Female1998",
        "gender": "F",
        "piperVoiceID": 31
    },
    {
        "name": "Male2314",
        "gender": "M",
        "piperVoiceID": 172
    },
    {
        "name": "Male3759",
        "gender": "M",
        "piperVoiceID": 42
    },
    {
        "name": "Female3244",
        "gender": "F",
        "piperVoiceID": 51
    },
    {
        "name": "Female3631",
        "gender": "F",
        "piperVoiceID": 71
    },
    {
        "name": "Male989",
        "gender": "M",
        "piperVoiceID": 61
    },
    {
        "name": "Female3885",
        "gender": "F",
        "piperVoiceID": 15
    },
    {
        "name": "Male2497",
        "gender": "M",
        "piperVoiceID": 24
    },
    {
        "name": "Female3731",
        "gender": "F",
        "piperVoiceID": 77
    },
    {
        "name": "Male2043",
        "gender": "M",
        "piperVoiceID": 55
    },
    {
        "name": "Male1613",
        "gender": "M",
        "piperVoiceID": 157
    },
    {
        "name": "Male1897",
        "gender": "M",
        "piperVoiceID": 45
    },
    {
        "name": "Female589",
        "gender": "F",
        "piperVoiceID": 30
    },
    {
        "name": "Female327",
        "gender": "F",
        "piperVoiceID": 50
    },
    {
        "name": "Female19",
        "gender": "F",
        "piperVoiceID": 48
    },
    {
        "name": "Male146",
        "gender": "M",
        "piperVoiceID": 27
    },
    {
        "name": "Male2946",
        "gender": "M",
        "piperVoiceID": 21
    },
    {
        "name": "Male4542",
        "gender": "M",
        "piperVoiceID": 29
    },
    {
        "name": "Male2422",
        "gender": "M",
        "piperVoiceID": 0
    },
    {
        "name": "Female3124",
        "gender": "F",
        "piperVoiceID": 54
    },
    {
        "name": "Male2677",
        "gender": "M",
        "piperVoiceID": 43
    },
    {
        "name": "Male3797",
        "gender": "M",
        "piperVoiceID": 32
    },
    {
        "name": "Male3503",
        "gender": "M",
        "piperVoiceID": 7
    },
    {
        "name": "Female3330",
        "gender": "F",
        "piperVoiceID": 180
    },
    {
        "name": "Female2840",
        "gender": "F",
        "piperVoiceID": 183
    },
    {
        "name": "Female2732",
        "gender": "F",
        "piperVoiceID": 143
    },
    {
        "name": "Female2506",
        "gender": "F",
        "piperVoiceID": 166
    },
    {
        "name": "Female2158",
        "gender": "F",
        "piperVoiceID": 144
    },
    {
        "name": "Female1724",
        "gender": "F",
        "piperVoiceID": 161
    },
    {
        "name": "Male3494",
        "gender": "M",
        "piperVoiceID": 20
    },
    {
        "name": "Male3276",
        "gender": "M",
        "piperVoiceID": 189
    },
    {
        "name": "Male5055",
        "gender": "M",
        "piperVoiceID": 6
    },
    {
        "name": "Female2859",
        "gender": "F",
        "piperVoiceID": 181
    },
    {
        "name": "Male3685",
        "gender": "M",
        "piperVoiceID": 226
    },
    {
        "name": "Female3698",
        "gender": "F",
        "piperVoiceID": 145
    },
    {
        "name": "Female3995",
        "gender": "F",
        "piperVoiceID": 234
    },
    {
        "name": "Female4153",
        "gender": "F",
        "piperVoiceID": 179
    },
    {
        "name": "Male4414",
        "gender": "M",
        "piperVoiceID": 167
    },
    {
        "name": "Male2234",
        "gender": "M",
        "piperVoiceID": 53
    },
    {
        "name": "Female4463",
        "gender": "F",
        "piperVoiceID": 130
    },
    {
        "name": "Female3990",
        "gender": "F",
        "piperVoiceID": 10
    },
    {
        "name": "Female4650",
        "gender": "F",
        "piperVoiceID": 78
    },
    {
        "name": "Male4396",
        "gender": "M",
        "piperVoiceID": 65
    },
    {
        "name": "Female4576",
        "gender": "F",
        "piperVoiceID": 153
    },
    {
        "name": "Female4468",
        "gender": "F",
        "piperVoiceID": 198
    },
    {
        "name": "Male4536",
        "gender": "M",
        "piperVoiceID": 1
    },
    {
        "name": "Female4533",
        "gender": "F",
        "piperVoiceID": 23
    },
    {
        "name": "Female5324",
        "gender": "F",
        "piperVoiceID": 52
    },
    {
        "name": "Male1033",
        "gender": "M",
        "piperVoiceID": 170
    },
    {
        "name": "Male5406",
        "gender": "M",
        "piperVoiceID": 182
    },
    {
        "name": "Female4512",
        "gender": "F",
        "piperVoiceID": 154
    },
    {
        "name": "Female6507",
        "gender": "F",
        "piperVoiceID": 5
    },
    {
        "name": "Male5675",
        "gender": "M",
        "piperVoiceID": 146
    },
    {
        "name": "Female5632",
        "gender": "F",
        "piperVoiceID": 76
    },
    {
        "name": "Female5405",
        "gender": "F",
        "piperVoiceID": 62
    },
    {
        "name": "Male5283",
        "gender": "M",
        "piperVoiceID": 22
    },
    {
        "name": "Male5819",
        "gender": "M",
        "piperVoiceID": 227
    },
    {
        "name": "Male6659",
        "gender": "M",
        "piperVoiceID": 141
    },
    {
        "name": "Male7194",
        "gender": "M",
        "piperVoiceID": 41
    },
    {
        "name": "Male6905",
        "gender": "M",
        "piperVoiceID": 178
    },
    {
        "name": "Male6315",
        "gender": "M",
        "piperVoiceID": 147
    },
    {
        "name": "Female6117",
        "gender": "F",
        "piperVoiceID": 214
    },
    {
        "name": "Male6448",
        "gender": "M",
        "piperVoiceID": 215
    },
    {
        "name": "Female6611",
        "gender": "F",
        "piperVoiceID": 199
    },
    {
        "name": "Male6646",
        "gender": "M",
        "piperVoiceID": 209
    },
    {
        "name": "Female6826",
        "gender": "F",
        "piperVoiceID": 173
    },
    {
        "name": "Male287",
        "gender": "M",
        "piperVoiceID": 158
    },
    {
        "name": "Male253",
        "gender": "M",
        "piperVoiceID": 39
    },
    {
        "name": "Female8337",
        "gender": "F",
        "piperVoiceID": 28
    },
    {
        "name": "Female8470",
        "gender": "F",
        "piperVoiceID": 17
    },
    {
        "name": "Female9610",
        "gender": "F",
        "piperVoiceID": 37
    },
    {
        "name": "Female6982",
        "gender": "F",
        "piperVoiceID": 160
    },
    {
        "name": "Female7006",
        "gender": "F",
        "piperVoiceID": 225
    },
    {
        "name": "Male6719",
        "gender": "M",
        "piperVoiceID": 44
    },
    {
        "name": "Male6952",
        "gender": "M",
        "piperVoiceID": 232
    },
    {
        "name": "Female7242",
        "gender": "F",
        "piperVoiceID": 70
    },
    {
        "name": "Male7328",
        "gender": "M",
        "piperVoiceID": 34
    },
    {
        "name": "Female7270",
        "gender": "F",
        "piperVoiceID": 196
    },
    {
        "name": "Female2909",
        "gender": "F",
        "piperVoiceID": 164
    },
    {
        "name": "Male7202",
        "gender": "M",
        "piperVoiceID": 149
    },
    {
        "name": "Female5823",
        "gender": "F",
        "piperVoiceID": 218
    },
    {
        "name": "Female8139",
        "gender": "F",
        "piperVoiceID": 57
    },
    {
        "name": "Female7479",
        "gender": "F",
        "piperVoiceID": 75
    },
    {
        "name": "Female7906",
        "gender": "F",
        "piperVoiceID": 73
    },
    {
        "name": "Female7486",
        "gender": "F",
        "piperVoiceID": 210
    },
    {
        "name": "Male7483",
        "gender": "M",
        "piperVoiceID": 195
    },
    {
        "name": "Female7515",
        "gender": "F",
        "piperVoiceID": 217
    },
    {
        "name": "Male7150",
        "gender": "M",
        "piperVoiceID": 231
    },
    {
        "name": "Female7449",
        "gender": "F",
        "piperVoiceID": 235
    },
    {
        "name": "Male5764",
        "gender": "M",
        "piperVoiceID": 168
    },
    {
        "name": "Female8305",
        "gender": "F",
        "piperVoiceID": 187
    },
    {
        "name": "Female7998",
        "gender": "F",
        "piperVoiceID": 35
    },
    {
        "name": "Female7579",
        "gender": "F",
        "piperVoiceID": 193
    },
    {
        "name": "Female2792",
        "gender": "F",
        "piperVoiceID": 202
    },
    {
        "name": "Female1474",
        "gender": "F",
        "piperVoiceID": 66
    },
    {
        "name": "Female8634",
        "gender": "F",
        "piperVoiceID": 155
    },
    {
        "name": "Male8427",
        "gender": "M",
        "piperVoiceID": 175
    },
    {
        "name": "Male8732",
        "gender": "M",
        "piperVoiceID": 206
    },
    {
        "name": "Female8704",
        "gender": "F",
        "piperVoiceID": 197
    },
    {
        "name": "Female8567",
        "gender": "F",
        "piperVoiceID": 219
    },
    {
        "name": "Male139",
        "gender": "M",
        "piperVoiceID": 67
    },
    {
        "name": "Male143",
        "gender": "M",
        "piperVoiceID": 56
    },
    {
        "name": "Female136",
        "gender": "F",
        "piperVoiceID": 68
    },
    {
        "name": "Male9207",
        "gender": "M",
        "piperVoiceID": 159
    },
    {
        "name": "Female10191",
        "gender": "F",
        "piperVoiceID": 162
    },
    {
        "name": "Female1091",
        "gender": "F",
        "piperVoiceID": 163
    },
    {
        "name": "Female9241",
        "gender": "F",
        "piperVoiceID": 185
    },
    {
        "name": "Female9287",
        "gender": "F",
        "piperVoiceID": 177
    },
    {
        "name": "Male8675",
        "gender": "M",
        "piperVoiceID": 194
    },
    {
        "name": "Female9515",
        "gender": "F",
        "piperVoiceID": 49
    },
    {
        "name": "Female9353",
        "gender": "F",
        "piperVoiceID": 228
    },
    {
        "name": "Male9538",
        "gender": "M",
        "piperVoiceID": 60
    },
    {
        "name": "Female9908",
        "gender": "F",
        "piperVoiceID": 72
    },
    {
        "name": "Male9168",
        "gender": "M",
        "piperVoiceID": 176
    },
    {
        "name": "Female1171",
        "gender": "F",
        "piperVoiceID": 74
    },
    {
        "name": "Male1965",
        "gender": "M",
        "piperVoiceID": 165
    },
    {
        "name": "Female1920",
        "gender": "F",
        "piperVoiceID": 184
    },
    {
        "name": "Male9646",
        "gender": "M",
        "piperVoiceID": 58
    },
    {
        "name": "Female10162",
        "gender": "F",
        "piperVoiceID": 204
    },
    {
        "name": "Female10163",
        "gender": "F",
        "piperVoiceID": 186
    },
    {
        "name": "Male10870",
        "gender": "M",
        "piperVoiceID": 128
    },
    {
        "name": "Female9514",
        "gender": "F",
        "piperVoiceID": 84
    },
    {
        "name": "Male13255",
        "gender": "M",
        "piperVoiceID": 116
    },
    {
        "name": "Male13494",
        "gender": "M",
        "piperVoiceID": 85
    },
    {
        "name": "Female13871",
        "gender": "F",
        "piperVoiceID": 106
    },
    {
        "name": "Female1946",
        "gender": "F",
        "piperVoiceID": 86
    },
    {
        "name": "Female3277",
        "gender": "F",
        "piperVoiceID": 87
    },
    {
        "name": "Female2974",
        "gender": "F",
        "piperVoiceID": 107
    },
    {
        "name": "Female1593",
        "gender": "F",
        "piperVoiceID": 93
    },
    {
        "name": "Female3862",
        "gender": "F",
        "piperVoiceID": 94
    },
    {
        "name": "Male4001",
        "gender": "M",
        "piperVoiceID": 135
    },
    {
        "name": "Male5595",
        "gender": "M",
        "piperVoiceID": 88
    },
    {
        "name": "Female5934",
        "gender": "F",
        "piperVoiceID": 108
    },
    {
        "name": "Female4730",
        "gender": "F",
        "piperVoiceID": 140
    },
    {
        "name": "Male5295",
        "gender": "M",
        "piperVoiceID": 121
    },
    {
        "name": "Male7002",
        "gender": "M",
        "piperVoiceID": 109
    },
    {
        "name": "Male7272",
        "gender": "M",
        "piperVoiceID": 124
    },
    {
        "name": "Female8769",
        "gender": "F",
        "piperVoiceID": 110
    },
    {
        "name": "Female8325",
        "gender": "F",
        "piperVoiceID": 133
    },
    {
        "name": "Male8743",
        "gender": "M",
        "piperVoiceID": 115
    },
    {
        "name": "Male135",
        "gender": "M",
        "piperVoiceID": 79
    },
    {
        "name": "Male138",
        "gender": "M",
        "piperVoiceID": 95
    },
    {
        "name": "Male145",
        "gender": "M",
        "piperVoiceID": 80
    },
    {
        "name": "Male137",
        "gender": "M",
        "piperVoiceID": 81
    },
    {
        "name": "Male141",
        "gender": "M",
        "piperVoiceID": 96
    },
    {
        "name": "Male9948",
        "gender": "M",
        "piperVoiceID": 97
    },
    {
        "name": "Female10349",
        "gender": "F",
        "piperVoiceID": 131
    },
    {
        "name": "Female1163",
        "gender": "F",
        "piperVoiceID": 98
    },
    {
        "name": "Female7320",
        "gender": "F",
        "piperVoiceID": 125
    },
    {
        "name": "Female1757",
        "gender": "F",
        "piperVoiceID": 82
    },
    {
        "name": "Male4705",
        "gender": "M",
        "piperVoiceID": 122
    },
    {
        "name": "Male1054",
        "gender": "M",
        "piperVoiceID": 99
    },
    {
        "name": "Male2252",
        "gender": "M",
        "piperVoiceID": 132
    },
    {
        "name": "Male1844",
        "gender": "M",
        "piperVoiceID": 100
    },
    {
        "name": "Female3588",
        "gender": "F",
        "piperVoiceID": 118
    },
    {
        "name": "Male3052",
        "gender": "M",
        "piperVoiceID": 134
    },
    {
        "name": "Male3363",
        "gender": "M",
        "piperVoiceID": 111
    },
    {
        "name": "Male3040",
        "gender": "M",
        "piperVoiceID": 112
    },
    {
        "name": "Female278",
        "gender": "F",
        "piperVoiceID": 89
    },
    {
        "name": "Male4748",
        "gender": "M",
        "piperVoiceID": 119
    },
    {
        "name": "Female4739",
        "gender": "F",
        "piperVoiceID": 138
    },
    {
        "name": "Male4911",
        "gender": "M",
        "piperVoiceID": 101
    },
    {
        "name": "Female6067",
        "gender": "F",
        "piperVoiceID": 113
    },
    {
        "name": "Female7120",
        "gender": "F",
        "piperVoiceID": 90
    },
    {
        "name": "Female7261",
        "gender": "F",
        "piperVoiceID": 102
    },
    {
        "name": "Female8223",
        "gender": "F",
        "piperVoiceID": 103
    },
    {
        "name": "Female8125",
        "gender": "F",
        "piperVoiceID": 123
    },
    {
        "name": "Female7456",
        "gender": "F",
        "piperVoiceID": 136
    },
    {
        "name": "Female8450",
        "gender": "F",
        "piperVoiceID": 120
    },
    {
        "name": "Male7406",
        "gender": "M",
        "piperVoiceID": 91
    },
    {
        "name": "Female7624",
        "gender": "F",
        "piperVoiceID": 104
    },
    {
        "name": "Male144",
        "gender": "M",
        "piperVoiceID": 105
    },
    {
        "name": "Male91",
        "gender": "M",
        "piperVoiceID": 83
    },
    {
        "name": "Male140",
        "gender": "M",
        "piperVoiceID": 137
    },
    {
        "name": "Female12379",
        "gender": "F",
        "piperVoiceID": 129
    },
    {
        "name": "Male11695",
        "gender": "M",
        "piperVoiceID": 92
    },
    {
        "name": "Female1660",
        "gender": "F",
        "piperVoiceID": 117
    },
    {
        "name": "Female1262",
        "gender": "F",
        "piperVoiceID": 127
    },
    {
        "name": "Female9494",
        "gender": "F",
        "piperVoiceID": 114
    },
    {
        "name": "Male1874",
        "gender": "M",
        "piperVoiceID": 126
    }
]